torchoptics/__init__.py
torchoptics/config.py
torchoptics/fields.py
torchoptics/optics_module.py
torchoptics/planar_grid.py
torchoptics/py.typed
torchoptics/system.py
torchoptics/type_defs.py
torchoptics/utils.py
torchoptics/visualization.py
torchoptics/elements/__init__.py
torchoptics/elements/beam_splitters.py
torchoptics/elements/detectors.py
torchoptics/elements/elements.py
torchoptics/elements/identity_element.py
torchoptics/elements/lens.py
torchoptics/elements/modulators.py
torchoptics/elements/polarized_modulators.py
torchoptics/elements/polarizers.py
torchoptics/elements/waveplates.py
torchoptics/functional/__init__.py
torchoptics/functional/functional.py
torchoptics/profiles/__init__.py
torchoptics/profiles/_profile_meshgrid.py
torchoptics/profiles/bessel.py
torchoptics/profiles/gratings.py
torchoptics/profiles/hermite_gaussian.py
torchoptics/profiles/laguerre_gaussian.py
torchoptics/profiles/lens_phase.py
torchoptics/profiles/shapes.py
torchoptics/profiles/spatial_coherence.py
torchoptics/profiles/special.py
torchoptics/profiles/waves.py
torchoptics/profiles/zernike.py
torchoptics/propagation/__init__.py
torchoptics/propagation/angular_spectrum_method.py
torchoptics/propagation/direct_integration_method.py
torchoptics/propagation/propagator.py
torchoptics-0.4.0.dist-info/licenses/LICENSE
torchoptics-0.4.0.dist-info/METADATA
torchoptics-0.4.0.dist-info/WHEEL
torchoptics-0.4.0.dist-info/top_level.txt
torchoptics-0.4.0.dist-info/RECORD
