Metadata-Version: 2.4
Name: torchoptics
Version: 0.4.0
Summary: Python library for differentiable Fourier optics simulations with PyTorch.
Author-email: Matthew Filipovich <matthew.filipovich@physics.ox.ac.uk>
License: MIT License
Project-URL: Homepage, https://github.com/MatthewFilipovich/torchoptics
Project-URL: Documentation, https://torchoptics.readthedocs.io/
Project-URL: Tracker, https://github.com/MatthewFilipovich/torchoptics/issues
Keywords: wave optics,PyTorch,machine learning,physics,microscopy,imaging,diffraction,holography,computational optics,Fourier optics,optical neural networks,inverse design,differentiable optics
Classifier: Programming Language :: Python :: 3
Classifier: Operating System :: OS Independent
Classifier: Intended Audience :: Science/Research
Classifier: Intended Audience :: Education
Classifier: Topic :: Scientific/Engineering :: Physics
Classifier: License :: OSI Approved :: MIT License
Requires-Python: >=3.9
License-File: LICENSE
Requires-Dist: torch
Requires-Dist: matplotlib
Provides-Extra: dev
Requires-Dist: coverage; extra == "dev"
Requires-Dist: pre-commit; extra == "dev"
Requires-Dist: pyright; extra == "dev"
Requires-Dist: pytest; extra == "dev"
Requires-Dist: ruff; extra == "dev"
Requires-Dist: scipy; extra == "dev"
Dynamic: license-file
